<?xml version="1.0" encoding="utf-8"?>
<CallableObject guid="f6aec692-a6b9-4c38-b495-7b50e7fc33b3" name="core.dpDocumentoTipoObterDados" description="Obter Dados do Tipo de Documento" namespace="GeneXus.Programs">
  <Signature name="par">
    <Parameter name="sdtDocumentoTipo">
      <Field name="sdtDocumentoTipo" description="sdt Documento Tipo">
        <Fields>
          <Field name="DocTipoID" description="Tipo do Documento">
            <Properties>
              <Property>
                <Name>Type</Name>
                <Value>Numeric</Value>
              </Property>
              <Property>
                <Name>Length</Name>
                <Value>9</Value>
              </Property>
              <Property>
                <Name>Picture</Name>
                <Value>ZZZ,ZZZ,ZZ9</Value>
              </Property>
            </Properties>
          </Field>
          <Field name="DocTipoSigla" description="Sigla">
            <Properties>
              <Property>
                <Name>Type</Name>
                <Value>VarChar</Value>
              </Property>
              <Property>
                <Name>Length</Name>
                <Value>20</Value>
              </Property>
            </Properties>
          </Field>
          <Field name="DocTipoNome" description="Descrição">
            <Properties>
              <Property>
                <Name>Type</Name>
                <Value>VarChar</Value>
              </Property>
              <Property>
                <Name>Length</Name>
                <Value>80</Value>
              </Property>
              <Property>
                <Name>Picture</Name>
                <Value>@!</Value>
              </Property>
            </Properties>
          </Field>
          <Field name="DocTipoAtivo" description="Ativo">
            <Properties>
              <Property>
                <Name>Type</Name>
                <Value>Boolean</Value>
              </Property>
            </Properties>
          </Field>
          <Field name="DocTipoDel" description="Registro Excluído">
            <Properties>
              <Property>
                <Name>Type</Name>
                <Value>Boolean</Value>
              </Property>
            </Properties>
          </Field>
          <Field name="DocTipoDelDataHora" description="Data/Hora da Exclusão">
            <Properties>
              <Property>
                <Name>Type</Name>
                <Value>DateTime</Value>
              </Property>
              <Property>
                <Name>Length</Name>
                <Value>10</Value>
              </Property>
              <Property>
                <Name>Decimals</Name>
                <Value>5</Value>
              </Property>
              <Property>
                <Name>Picture</Name>
                <Value>99/99/9999 99:99</Value>
              </Property>
            </Properties>
          </Field>
          <Field name="DocTipoDelData" description="Data de Exclusão">
            <Properties>
              <Property>
                <Name>Type</Name>
                <Value>Date</Value>
              </Property>
              <Property>
                <Name>Length</Name>
                <Value>8</Value>
              </Property>
              <Property>
                <Name>Picture</Name>
                <Value>99/99/99</Value>
              </Property>
            </Properties>
          </Field>
          <Field name="DocTipoDelHora" description="Hora de Exclusão">
            <Properties>
              <Property>
                <Name>Type</Name>
                <Value>DateTime</Value>
              </Property>
              <Property>
                <Name>Length</Name>
                <Value>0</Value>
              </Property>
              <Property>
                <Name>Decimals</Name>
                <Value>5</Value>
              </Property>
              <Property>
                <Name>Picture</Name>
                <Value>99:99</Value>
              </Property>
            </Properties>
          </Field>
          <Field name="DocTipoDelUsuID" description="Usuário ID de Exclusão">
            <Properties>
              <Property>
                <Name>Type</Name>
                <Value>Character</Value>
              </Property>
              <Property>
                <Name>Length</Name>
                <Value>40</Value>
              </Property>
            </Properties>
          </Field>
          <Field name="DocTipoDelUsuNome" description="Nome do Usuário de Exclusão">
            <Properties>
              <Property>
                <Name>Type</Name>
                <Value>VarChar</Value>
              </Property>
              <Property>
                <Name>Length</Name>
                <Value>80</Value>
              </Property>
              <Property>
                <Name>Picture</Name>
                <Value>@!</Value>
              </Property>
            </Properties>
          </Field>
        </Fields>
      </Field>
    </Parameter>
    <Parameter name="ReturnValue" accessor="out" collection="true">
      <Field name="sdtDocumentoTipo" description="sdt Documento Tipo">
        <Fields>
          <Field name="DocTipoID" description="Tipo do Documento">
            <Properties>
              <Property>
                <Name>Type</Name>
                <Value>Numeric</Value>
              </Property>
              <Property>
                <Name>Length</Name>
                <Value>9</Value>
              </Property>
              <Property>
                <Name>Picture</Name>
                <Value>ZZZ,ZZZ,ZZ9</Value>
              </Property>
            </Properties>
          </Field>
          <Field name="DocTipoSigla" description="Sigla">
            <Properties>
              <Property>
                <Name>Type</Name>
                <Value>VarChar</Value>
              </Property>
              <Property>
                <Name>Length</Name>
                <Value>20</Value>
              </Property>
            </Properties>
          </Field>
          <Field name="DocTipoNome" description="Descrição">
            <Properties>
              <Property>
                <Name>Type</Name>
                <Value>VarChar</Value>
              </Property>
              <Property>
                <Name>Length</Name>
                <Value>80</Value>
              </Property>
              <Property>
                <Name>Picture</Name>
                <Value>@!</Value>
              </Property>
            </Properties>
          </Field>
          <Field name="DocTipoAtivo" description="Ativo">
            <Properties>
              <Property>
                <Name>Type</Name>
                <Value>Boolean</Value>
              </Property>
            </Properties>
          </Field>
          <Field name="DocTipoDel" description="Registro Excluído">
            <Properties>
              <Property>
                <Name>Type</Name>
                <Value>Boolean</Value>
              </Property>
            </Properties>
          </Field>
          <Field name="DocTipoDelDataHora" description="Data/Hora da Exclusão">
            <Properties>
              <Property>
                <Name>Type</Name>
                <Value>DateTime</Value>
              </Property>
              <Property>
                <Name>Length</Name>
                <Value>10</Value>
              </Property>
              <Property>
                <Name>Decimals</Name>
                <Value>5</Value>
              </Property>
              <Property>
                <Name>Picture</Name>
                <Value>99/99/9999 99:99</Value>
              </Property>
            </Properties>
          </Field>
          <Field name="DocTipoDelData" description="Data de Exclusão">
            <Properties>
              <Property>
                <Name>Type</Name>
                <Value>Date</Value>
              </Property>
              <Property>
                <Name>Length</Name>
                <Value>8</Value>
              </Property>
              <Property>
                <Name>Picture</Name>
                <Value>99/99/99</Value>
              </Property>
            </Properties>
          </Field>
          <Field name="DocTipoDelHora" description="Hora de Exclusão">
            <Properties>
              <Property>
                <Name>Type</Name>
                <Value>DateTime</Value>
              </Property>
              <Property>
                <Name>Length</Name>
                <Value>0</Value>
              </Property>
              <Property>
                <Name>Decimals</Name>
                <Value>5</Value>
              </Property>
              <Property>
                <Name>Picture</Name>
                <Value>99:99</Value>
              </Property>
            </Properties>
          </Field>
          <Field name="DocTipoDelUsuID" description="Usuário ID de Exclusão">
            <Properties>
              <Property>
                <Name>Type</Name>
                <Value>Character</Value>
              </Property>
              <Property>
                <Name>Length</Name>
                <Value>40</Value>
              </Property>
            </Properties>
          </Field>
          <Field name="DocTipoDelUsuNome" description="Nome do Usuário de Exclusão">
            <Properties>
              <Property>
                <Name>Type</Name>
                <Value>VarChar</Value>
              </Property>
              <Property>
                <Name>Length</Name>
                <Value>80</Value>
              </Property>
              <Property>
                <Name>Picture</Name>
                <Value>@!</Value>
              </Property>
            </Properties>
          </Field>
        </Fields>
      </Field>
    </Parameter>
  </Signature>
</CallableObject>